dnamlops/__init__.py
dnamlops/evidently/__init__.py
dnamlops/evidently/__main__.py
dnamlops/evidently/_config.py
dnamlops/evidently/_version.py
dnamlops/evidently/base_metric.py
dnamlops/evidently/analyzers/__init__.py
dnamlops/evidently/analyzers/base_analyzer.py
dnamlops/evidently/analyzers/cat_target_drift_analyzer.py
dnamlops/evidently/analyzers/classification_performance_analyzer.py
dnamlops/evidently/analyzers/data_drift_analyzer.py
dnamlops/evidently/analyzers/data_quality_analyzer.py
dnamlops/evidently/analyzers/num_target_drift_analyzer.py
dnamlops/evidently/analyzers/prob_classification_performance_analyzer.py
dnamlops/evidently/analyzers/prob_distribution_analyzer.py
dnamlops/evidently/analyzers/regression_performance_analyzer.py
dnamlops/evidently/calculations/__init__.py
dnamlops/evidently/calculations/classification_performance.py
dnamlops/evidently/calculations/data_drift.py
dnamlops/evidently/calculations/data_integration.py
dnamlops/evidently/calculations/data_quality.py
dnamlops/evidently/calculations/regression_performance.py
dnamlops/evidently/calculations/utils.py
dnamlops/evidently/calculations/stattests/__init__.py
dnamlops/evidently/calculations/stattests/anderson_darling_stattest.py
dnamlops/evidently/calculations/stattests/chisquare_stattest.py
dnamlops/evidently/calculations/stattests/cramer_von_mises_stattest.py
dnamlops/evidently/calculations/stattests/energy_distance.py
dnamlops/evidently/calculations/stattests/epps_singleton_stattest.py
dnamlops/evidently/calculations/stattests/fisher_exact_stattest.py
dnamlops/evidently/calculations/stattests/g_stattest.py
dnamlops/evidently/calculations/stattests/hellinger_distance.py
dnamlops/evidently/calculations/stattests/jensenshannon.py
dnamlops/evidently/calculations/stattests/kl_div.py
dnamlops/evidently/calculations/stattests/ks_stattest.py
dnamlops/evidently/calculations/stattests/mann_whitney_urank_stattest.py
dnamlops/evidently/calculations/stattests/mmd_stattest.py
dnamlops-0.0.3.dist-info/LICENSE
dnamlops-0.0.3.dist-info/METADATA
dnamlops-0.0.3.dist-info/WHEEL
dnamlops-0.0.3.dist-info/top_level.txt
dnamlops-0.0.3.dist-info/RECORD
